pytenzir/__init__.py
pytenzir/apps/thehive.py
pytenzir/tenzir/__init__.py
pytenzir/tenzir/cli.py
pytenzir/tenzir/convert.py
pytenzir/tenzir/tenzir.py
pytenzir/utils/arrow.py
pytenzir/utils/asyncio.py
pytenzir/utils/config.py
pytenzir/utils/logging.py
pytenzir-4.5.0.dist-info/WHEEL
pytenzir-4.5.0.dist-info/entry_points.txt
pytenzir-4.5.0.dist-info/METADATA
pytenzir-4.5.0.dist-info/RECORD
