Metadata-Version: 2.1
Name: pytenzir
Version: 4.5.0
Summary: A security telemetry engine for detection and response
Home-page: https://tenzir.com
License: BSD-3-Clause
Author: Tenzir
Author-email: engineering@tenzir.com
Maintainer: Tenzir
Maintainer-email: engineering@tenzir.com
Requires-Python: >=3.10,<4.0
Classifier: Development Status :: 3 - Alpha
Classifier: Environment :: Plugins
Classifier: License :: OSI Approved :: BSD License
Classifier: Operating System :: MacOS :: MacOS X
Classifier: Operating System :: POSIX :: Linux
Classifier: Programming Language :: Python :: 3
Classifier: Programming Language :: Python :: 3.10
Classifier: Programming Language :: Python :: 3.11
Classifier: Topic :: Scientific/Engineering :: Information Analysis
Classifier: Topic :: Scientific/Engineering :: Interface Engine/Protocol Translator
Classifier: Topic :: Security
Classifier: Topic :: Software Development :: Object Brokering
Classifier: Topic :: System :: Distributed Computing
Provides-Extra: thehive
Requires-Dist: aiohttp (>=3.8,<4.0) ; extra == "thehive"
Requires-Dist: coloredlogs (>=15.0,<16.0)
Requires-Dist: dynaconf (>=3.2,<4.0)
Requires-Dist: numpy (>=1.24,<2.0)
Requires-Dist: pandas (>=1.5,<3.0)
Requires-Dist: pyarrow (>=11,<15)
Project-URL: Documentation, https://tenzir.com/docs
Project-URL: Repository, https://github.com/tenzir/tenzir
